ywh2bt/__init__.py
ywh2bt/cli/__init__.py
ywh2bt/cli/commands/__init__.py
ywh2bt/cli/commands/convert.py
ywh2bt/cli/commands/schema.py
ywh2bt/cli/commands/synchronize.py
ywh2bt/cli/commands/test.py
ywh2bt/cli/commands/validate.py
ywh2bt/cli/error.py
ywh2bt/cli/listener.py
ywh2bt/cli/main.py
ywh2bt/core/__init__.py
ywh2bt/core/api/__init__.py
ywh2bt/core/api/client.py
ywh2bt/core/api/formatter/__init__.py
ywh2bt/core/api/formatter/formatter.py
ywh2bt/core/api/formatter/markdown.py
ywh2bt/core/api/mapping.py
ywh2bt/core/api/models/__init__.py
ywh2bt/core/api/models/report.py
ywh2bt/core/api/tracker.py
ywh2bt/core/api/trackers/__init__.py
ywh2bt/core/api/trackers/github/__init__.py
ywh2bt/core/api/trackers/github/attachment.py
ywh2bt/core/api/trackers/github/tracker.py
ywh2bt/core/api/trackers/gitlab.py
ywh2bt/core/api/trackers/jira/__init__.py
ywh2bt/core/api/trackers/jira/formatter.py
ywh2bt/core/api/trackers/jira/tracker.py
ywh2bt/core/api/trackers/servicenow/__init__.py
ywh2bt/core/api/trackers/servicenow/formatter.py
ywh2bt/core/api/trackers/servicenow/model.py
ywh2bt/core/api/trackers/servicenow/tracker.py
ywh2bt/core/api/yeswehack.py
ywh2bt/core/configuration/__init__.py
ywh2bt/core/configuration/attribute.py
ywh2bt/core/configuration/error.py
ywh2bt/core/configuration/exportable.py
ywh2bt/core/configuration/headers.py
ywh2bt/core/configuration/root.py
ywh2bt/core/configuration/subtypable.py
ywh2bt/core/configuration/tracker.py
ywh2bt/core/configuration/trackers/__init__.py
ywh2bt/core/configuration/trackers/github.py
ywh2bt/core/configuration/trackers/gitlab.py
ywh2bt/core/configuration/trackers/jira.py
ywh2bt/core/configuration/trackers/servicenow.py
ywh2bt/core/configuration/validatable.py
ywh2bt/core/configuration/validator.py
ywh2bt/core/configuration/yeswehack.py
ywh2bt/core/converter/__init__.py
ywh2bt/core/converter/html2jira.py
ywh2bt/core/converter/jira2markdown.py
ywh2bt/core/core.py
ywh2bt/core/crypt/__init__.py
ywh2bt/core/crypt/decrypt.py
ywh2bt-2.13.0.dist-info/METADATA
ywh2bt-2.13.0.dist-info/WHEEL
ywh2bt-2.13.0.dist-info/entry_points.txt
ywh2bt-2.13.0.dist-info/RECORD
