Metadata-Version: 2.1
Name: ywh2bt
Version: 2.13.0
Summary: ywh2bt - YesWeHack to Bug Tracker
Home-page: https://github.com/yeswehack/ywh2bugtracker
Author: m.honel
Author-email: m.honel@yeswehack.com
Maintainer: YesWeHack
Maintainer-email: project@yeswehack.com
Requires-Python: >=3.7.0,<3.13
Classifier: Environment :: Console
Classifier: Intended Audience :: Customer Service
Classifier: Intended Audience :: End Users/Desktop
Classifier: Operating System :: OS Independent
Classifier: Programming Language :: Python :: 3
Classifier: Programming Language :: Python :: 3.7
Classifier: Programming Language :: Python :: 3.8
Classifier: Programming Language :: Python :: 3.9
Classifier: Programming Language :: Python :: 3.10
Classifier: Programming Language :: Python :: 3.11
Classifier: Programming Language :: Python :: 3.12
Classifier: Topic :: Security
Classifier: Topic :: Software Development :: Bug Tracking
Classifier: Typing :: Typed
Provides-Extra: gui
Requires-Dist: PyGithub (>=1.53,<2.0)
Requires-Dist: aiohttp (>=3.8.0,<4.0.0) ; python_version < "3.8"
Requires-Dist: aiohttp (>=3.9.0,<4.0.0) ; python_version >= "3.8"
Requires-Dist: aiosnow (>=0.6.0,<0.7.0)
Requires-Dist: beautifulsoup4 (>=4.9.3,<5.0.0)
Requires-Dist: frozenlist (>=1.3.0,<2.0.0) ; python_version < "3.8"
Requires-Dist: frozenlist (>=1.4.0,<2.0.0) ; python_version >= "3.8"
Requires-Dist: html2text (>=2020.1.16,<2021.0.0)
Requires-Dist: jira (>=3.2.0,<3.3.0) ; python_version < "3.8"
Requires-Dist: jira (>=3.5.0,<4.0.0) ; python_version >= "3.8"
Requires-Dist: lxml (>=4.5.2,<5.0.0)
Requires-Dist: markdown (>=3.0.0,<4.0.0) ; python_version >= "3.8"
Requires-Dist: markdown (>=3.3.3,<4.0.0) ; python_version < "3.8"
Requires-Dist: multidict (>6.0.4)
Requires-Dist: pyside6 (>=6.5.0,<7.0.0) ; (python_version < "3.12") and (extra == "gui")
Requires-Dist: pyside6 (>=6.6.0,<7.0.0) ; (python_version >= "3.12") and (extra == "gui")
Requires-Dist: python-gitlab (>=2.5.0,<3.0.0)
Requires-Dist: requests (>=2.24.0,<3.0.0)
Requires-Dist: requests-toolbelt (>=0.9.1,<0.10.0)
Requires-Dist: ruamel.yaml (>=0.16.12,<0.17.0)
Requires-Dist: setuptools (>=69.0.2,<70.0.0) ; python_version >= "3.12"
Requires-Dist: singledispatchmethod (>=1.0,<2.0)
Requires-Dist: tomlkit (>=0.7.0,<0.8.0)
Requires-Dist: types-Markdown
Requires-Dist: types-chardet
Requires-Dist: types-requests
Requires-Dist: types-setuptools
Requires-Dist: typing-extensions
Requires-Dist: urllib3 (<=1.26.15)
Requires-Dist: yeswehack (>=0.8.11)
Project-URL: Repository, https://github.com/yeswehack/ywh2bugtracker
